{
  "key": "LND-152",
  "summary": "Blind75-NeetCode",
  "status": "In Progress",
  "labels": [
    "blind75",
    "interview_prep",
    "leetcode",
    "neetcode"
  ]
}
{
  "key": "LND-150",
  "summary": "19 - Rohit - Generate Parentheses",
  "status": "To Do",
  "labels": [
    "Medium",
    "Stack"
  ]
}
{
  "key": "LND-145",
  "summary": "25 - Rohit - Reverse Linked List",
  "status": "To Do",
  "labels": [
    "Easy",
    "Linked_List"
  ]
}
{
  "key": "LND-143",
  "summary": "24 - Rohit - Search in Rotated Sorted Array",
  "status": "To Do",
  "labels": [
    "Binary_Search",
    "Medium"
  ]
}
{
  "key": "LND-141",
  "summary": "27 - Rohit - Reorder List",
  "status": "To Do",
  "labels": [
    "Linked_List",
    "Medium"
  ]
}
{
  "key": "LND-140",
  "summary": "26 - Rohit - Merge Two Sorted Lists",
  "status": "To Do",
  "labels": [
    "Easy",
    "Linked_List"
  ]
}
{
  "key": "LND-139",
  "summary": "21 - Rohit - Binary Search",
  "status": "To Do",
  "labels": [
    "Binary_Search",
    "Easy"
  ]
}
{
  "key": "LND-136",
  "summary": "20 - Rohit - Daily Temperatures",
  "status": "To Do",
  "labels": [
    "Medium",
    "Stack"
  ]
}
{
  "key": "LND-134",
  "summary": "23 - Rohit - Find Minimum in Rotated Sorted Array",
  "status": "To Do",
  "labels": [
    "Binary_Search",
    "Medium"
  ]
}
{
  "key": "LND-133",
  "summary": "22 - Rohit - Search a 2D Matrix",
  "status": "To Do",
  "labels": [
    "Binary_Search",
    "Medium"
  ]
}
{
  "key": "LND-132",
  "summary": "28 - Rohit - Remove Nth Node From End of List",
  "status": "To Do",
  "labels": [
    "Linked_List",
    "Medium"
  ]
}
{
  "key": "LND-127",
  "summary": "14 - Rohit - Longest Repeating Character Replacement",
  "status": "To Do",
  "labels": [
    "Medium",
    "Sliding_Window"
  ]
}
{
  "key": "LND-126",
  "summary": "13 - Rohit - Longest Substring Without Repeating Characters",
  "status": "To Do",
  "labels": [
    "Medium",
    "Sliding_Window"
  ]
}
{
  "key": "LND-124",
  "summary": "16 - Rohit - Valid Parentheses",
  "status": "To Do",
  "labels": [
    "Easy",
    "Stack"
  ]
}
{
  "key": "LND-122",
  "summary": "15 - Rohit - Minimum Window Substring",
  "status": "To Do",
  "labels": [
    "Hard",
    "Sliding_Window"
  ]
}
{
  "key": "LND-121",
  "summary": "10 - Rohit - 3Sum",
  "status": "To Do",
  "labels": [
    "Medium",
    "Two_Pointers"
  ]
}
{
  "key": "LND-119",
  "summary": "9 - Rohit - Valid Palindrome",
  "status": "To Do",
  "labels": [
    "Easy",
    "Two_Pointers"
  ]
}
{
  "key": "LND-117",
  "summary": "12 - Rohit - Best Time to Buy and Sell Stock",
  "status": "To Do",
  "labels": [
    "Easy",
    "Sliding_Window"
  ]
}
{
  "key": "LND-116",
  "summary": "11 - Rohit - Container With Most Water",
  "status": "To Do",
  "labels": [
    "Medium",
    "Two_Pointers"
  ]
}
{
  "key": "LND-114",
  "summary": "18 - Rohit - Evaluate Reverse Polish Notation",
  "status": "To Do",
  "labels": [
    "Medium",
    "Stack"
  ]
}
{
  "key": "LND-112",
  "summary": "17 - Rohit - Min Stack",
  "status": "To Do",
  "labels": [
    "Medium",
    "Stack"
  ]
}
{
  "key": "LND-96",
  "summary": "72 - Rohit - Number of 1 Bits",
  "status": "To Do",
  "labels": [
    "Bit_Manipulation",
    "Easy"
  ]
}
{
  "key": "LND-94",
  "summary": "71 - Rohit - Set Matrix Zeroes",
  "status": "To Do",
  "labels": [
    "Math_Geometry",
    "Medium"
  ]
}
{
  "key": "LND-93",
  "summary": "74 - Rohit - Reverse Bits",
  "status": "To Do",
  "labels": [
    "Bit_Manipulation",
    "Easy"
  ]
}
{
  "key": "LND-91",
  "summary": "73 - Rohit - Counting Bits",
  "status": "To Do",
  "labels": [
    "Bit_Manipulation",
    "Easy"
  ]
}
{
  "key": "LND-90",
  "summary": "70 - Rohit - Spiral Matrix",
  "status": "To Do",
  "labels": [
    "Math_Geometry",
    "Medium"
  ]
}
{
  "key": "LND-89",
  "summary": "69 - Rohit - Rotate Image",
  "status": "To Do",
  "labels": [
    "Math_Geometry",
    "Medium"
  ]
}
{
  "key": "LND-85",
  "summary": "75 - Rohit - Missing Number",
  "status": "To Do",
  "labels": [
    "Bit_Manipulation",
    "Easy"
  ]
}
{
  "key": "LND-78",
  "summary": "61 - Rohit - Unique Paths",
  "status": "To Do",
  "labels": [
    "2-D_Dynamic_Programming",
    "Medium"
  ]
}
{
  "key": "LND-76",
  "summary": "60 - Rohit - Longest Increasing Subsequence",
  "status": "To Do",
  "labels": [
    "1-D_Dynamic_Programming",
    "Medium"
  ]
}
{
  "key": "LND-74",
  "summary": "63 - Rohit - Jump Game",
  "status": "To Do",
  "labels": [
    "Greedy",
    "Medium"
  ]
}
{
  "key": "LND-73",
  "summary": "62 - Rohit - Longest Common Subsequence",
  "status": "To Do",
  "labels": [
    "2-D_Dynamic_Programming",
    "Medium"
  ]
}
{
  "key": "LND-72",
  "summary": "59 - Rohit - Word Break",
  "status": "To Do",
  "labels": [
    "1-D_Dynamic_Programming",
    "Medium"
  ]
}
{
  "key": "LND-69",
  "summary": "68 - Rohit - Meeting Rooms II",
  "status": "To Do",
  "labels": [
    "Intervals",
    "Medium"
  ]
}
{
  "key": "LND-67",
  "summary": "65 - Rohit - Merge Intervals",
  "status": "To Do",
  "labels": [
    "Intervals",
    "Medium"
  ]
}
{
  "key": "LND-65",
  "summary": "64 - Rohit - Insert Interval",
  "status": "To Do",
  "labels": [
    "Intervals",
    "Medium"
  ]
}
{
  "key": "LND-63",
  "summary": "67 - Rohit - Meeting Rooms",
  "status": "To Do",
  "labels": [
    "Easy",
    "Intervals"
  ]
}
{
  "key": "LND-62",
  "summary": "66 - Rohit - Non-overlapping Intervals",
  "status": "To Do",
  "labels": [
    "Intervals",
    "Medium"
  ]
}
{
  "key": "LND-59",
  "summary": "50 - Rohit - Number of Connected Components In An Undirected Graph",
  "status": "To Do",
  "labels": [
    "Graphs",
    "Medium"
  ]
}
{
  "key": "LND-58",
  "summary": "49 - Rohit - Course Schedule",
  "status": "To Do",
  "labels": [
    "Graphs",
    "Medium"
  ]
}
{
  "key": "LND-56",
  "summary": "52 - Rohit - House Robber",
  "status": "To Do",
  "labels": [
    "1-D_Dynamic_Programming",
    "Medium"
  ]
}
{
  "key": "LND-55",
  "summary": "51 - Rohit - Climbing Stairs",
  "status": "To Do",
  "labels": [
    "1-D_Dynamic_Programming",
    "Easy"
  ]
}
{
  "key": "LND-52",
  "summary": "58 - Rohit - Maximum Product Subarray",
  "status": "To Do",
  "labels": [
    "1-D_Dynamic_Programming",
    "Medium"
  ]
}
{
  "key": "LND-50",
  "summary": "57 - Rohit - Coin Change",
  "status": "To Do",
  "labels": [
    "1-D_Dynamic_Programming",
    "Medium"
  ]
}
{
  "key": "LND-48",
  "summary": "54 - Rohit - Longest Palindromic Substring",
  "status": "To Do",
  "labels": [
    "1-D_Dynamic_Programming",
    "Medium"
  ]
}
{
  "key": "LND-47",
  "summary": "53 - Rohit - House Robber II",
  "status": "To Do",
  "labels": [
    "1-D_Dynamic_Programming",
    "Medium"
  ]
}
{
  "key": "LND-45",
  "summary": "56 - Rohit - Decode Ways",
  "status": "To Do",
  "labels": [
    "1-D_Dynamic_Programming",
    "Medium"
  ]
}
{
  "key": "LND-43",
  "summary": "55 - Rohit - Palindromic Substrings",
  "status": "To Do",
  "labels": [
    "1-D_Dynamic_Programming",
    "Medium"
  ]
}
{
  "key": "LND-39",
  "summary": "39 - Rohit - Binary Tree Maximum Path Sum",
  "status": "To Do",
  "labels": [
    "Hard",
    "Trees"
  ]
}
{
  "key": "LND-37",
  "summary": "6 - Rohit - Product of Array Except Self",
  "status": "To Do",
  "labels": [
    "Array_Hashing",
    "Medium"
  ]
}
{
  "key": "LND-36",
  "summary": "5 - Rohit - Top K Frequent Elements",
  "status": "To Do",
  "labels": [
    "Array_Hashing",
    "Medium"
  ]
}
{
  "key": "LND-35",
  "summary": "8 - Rohit - Longest Consecutive Sequence",
  "status": "To Do",
  "labels": [
    "Array_Hashing",
    "Medium"
  ]
}
{
  "key": "LND-34",
  "summary": "41 - Rohit - Design Add and Search Words Data Structure",
  "status": "To Do",
  "labels": [
    "Medium",
    "Tries"
  ]
}
{
  "key": "LND-32",
  "summary": "7 - Rohit - Encode and Decode Strings",
  "status": "To Do",
  "labels": [
    "Array_Hashing",
    "Medium"
  ]
}
{
  "key": "LND-31",
  "summary": "40 - Rohit - Implement Trie (Prefix Tree)",
  "status": "To Do",
  "labels": [
    "Medium",
    "Tries"
  ]
}
{
  "key": "LND-30",
  "summary": "2 - Rohit - Contains Duplicate",
  "status": "In Progress",
  "labels": [
    "Array_Hashing",
    "Easy"
  ]
}
{
  "key": "LND-29",
  "summary": "1 - Rohit - Two Sum",
  "status": "In Progress",
  "labels": [
    "Array_Hashing",
    "Easy"
  ]
}
{
  "key": "LND-28",
  "summary": "4 - Rohit - Group Anagrams",
  "status": "To Do",
  "labels": [
    "Array_Hashing",
    "Medium"
  ]
}
{
  "key": "LND-27",
  "summary": "3 - Rohit - Valid Anagram",
  "status": "To Do",
  "labels": [
    "Array_Hashing",
    "Easy"
  ]
}
{
  "key": "LND-25",
  "summary": "47 - Rohit - Clone Graph",
  "status": "To Do",
  "labels": [
    "Graphs",
    "Medium"
  ]
}
{
  "key": "LND-24",
  "summary": "46 - Rohit - Number of Islands",
  "status": "To Do",
  "labels": [
    "Graphs",
    "Medium"
  ]
}
{
  "key": "LND-23",
  "summary": "48 - Rohit - Pacific Atlantic Water Flow",
  "status": "To Do",
  "labels": [
    "Graphs",
    "Medium"
  ]
}
{
  "key": "LND-22",
  "summary": "43 - Rohit - Find Median from Data Stream",
  "status": "To Do",
  "labels": [
    "Hard",
    "Heap_/_Priority_Queue"
  ]
}
{
  "key": "LND-20",
  "summary": "42 - Rohit - Word Search II",
  "status": "To Do",
  "labels": [
    "Hard",
    "Tries"
  ]
}
{
  "key": "LND-19",
  "summary": "45 - Rohit - Word Search",
  "status": "To Do",
  "labels": [
    "Backtracking",
    "Medium"
  ]
}
{
  "key": "LND-17",
  "summary": "44 - Rohit - Combination Sum",
  "status": "To Do",
  "labels": [
    "Backtracking",
    "Medium"
  ]
}
{
  "key": "LND-16",
  "summary": "30 - Rohit - Merge k Sorted Lists",
  "status": "To Do",
  "labels": [
    "Hard",
    "Linked_List"
  ]
}
{
  "key": "LND-14",
  "summary": "29 - Rohit - Linked List Cycle",
  "status": "To Do",
  "labels": [
    "Easy",
    "Linked_List"
  ]
}
{
  "key": "LND-13",
  "summary": "36 - Rohit - Binary Tree Level Order Traversal",
  "status": "To Do",
  "labels": [
    "Medium",
    "Trees"
  ]
}
{
  "key": "LND-12",
  "summary": "35 - Rohit - Lowest Common Ancestor of a Binary Search Tree",
  "status": "To Do",
  "labels": [
    "Easy",
    "Trees"
  ]
}
{
  "key": "LND-10",
  "summary": "38 - Rohit - Kth Smallest Element in a BST",
  "status": "To Do",
  "labels": [
    "Medium",
    "Trees"
  ]
}
{
  "key": "LND-9",
  "summary": "37 - Rohit - Validate Binary Search Tree",
  "status": "To Do",
  "labels": [
    "Medium",
    "Trees"
  ]
}
{
  "key": "LND-7",
  "summary": "32 - Rohit - Maximum Depth of Binary Tree",
  "status": "To Do",
  "labels": [
    "Easy",
    "Trees"
  ]
}
{
  "key": "LND-6",
  "summary": "31 - Rohit - Invert Binary Tree",
  "status": "To Do",
  "labels": [
    "Easy",
    "Trees"
  ]
}
{
  "key": "LND-4",
  "summary": "34 - Rohit - Subtree of Another Tree",
  "status": "To Do",
  "labels": [
    "Easy",
    "Trees"
  ]
}
{
  "key": "LND-3",
  "summary": "33 - Rohit - Same Tree",
  "status": "To Do",
  "labels": [
    "Easy",
    "Trees"
  ]
}
{
  "key": "LND-1",
  "summary": "First Task",
  "status": "Done",
  "labels": []
}
